LBExporters-0.1.1.dist-info/METADATA
LBExporters-0.1.1.dist-info/RECORD
LBExporters-0.1.1.dist-info/WHEEL
LBExporters-0.1.1.dist-info/top_level.txt
labelbox2coco/__init__.py
labelbox2pascal/__init__.py
