Metadata-Version: 2.1
Name: LBExporters
Version: 0.1.1
Summary: Converters from Labelbox exports to other common foramts
Home-page: UNKNOWN
License: Apache 2.0
Platform: UNKNOWN
Provides-Extra: dev
Requires-Dist: jinja2
Requires-Dist: pillow
Requires-Dist: requests
Requires-Dist: shapely
Provides-Extra: dev
Requires-Dist: pytest; extra == 'dev'
Requires-Dist: xmltodict; extra == 'dev'
